{
    "dac_map": {
        "DAC0": "00",
        "DAC1": "01",
        "DAC2": "02",
        "DAC3": "03",
        "DAC4": "10",
        "DAC5": "11",
        "DAC6": "12",
        "DAC7": "13",
        "DAC8": "20",
        "DAC9": "21",
        "DAC10": "22",
        "DAC11": "23",
        "DAC12": "30",
        "DAC13": "31",
        "DAC14": "32",
        "DAC15": "33"
    },
    "adc_map": {
        "ADC0": "00",
        "ADC1": "01",
        "ADC2": "02",
        "ADC3": "03",
        "ADC4": "10",
        "ADC5": "11",
        "ADC6": "12",
        "ADC7": "13"
    }
}
